README.md
setup.py
dubbo/__init__.py
dubbo/client.py
dubbo/errors.py
dubbo/java_class.py
dubbo/server.py
dubbo/utils.py
dubbo/codec/__init__.py
dubbo/codec/hessian2.py
dubbo_py.egg-info/PKG-INFO
dubbo_py.egg-info/SOURCES.txt
dubbo_py.egg-info/dependency_links.txt
dubbo_py.egg-info/requires.txt
dubbo_py.egg-info/top_level.txt