Metadata-Version: 2.1
Name: dubbo-py
Version: 0.2.2
Summary: dubbo adaptor for python
Home-page: https://github.com/feiyuw/dubbo-py.git
Author: Zhang Yu
Author-email: feiyuw@gmail.com
License: UNKNOWN
Platform: any
Requires-Python: >=3.5
